{
    "renda": {
        "$0 a $15k": {
            "garantia": {
                "Nenhuma": "Alto",
                "Adequada": "Moderado"
            }
        },
        "$15 a $35k": {
            "garantia": {
                "Nenhuma": {
                    "divida": {
                        "Alta": {
                            "historia_de_credito": {
                                "Desconhecida": "Alto",
                                "Boa": "Moderado",
                                "Ruim": "Alto"
                            }
                        },
                        "Baixa": "Moderado"
                    }
                },
                "Adequada": {
                    "divida": {
                        "Baixa": "Moderado",
                        "Alta": "Baixo"
                    }
                }
            }
        },
        "Acima de $35k": {
            "garantia": {
                "Nenhuma": "Baixo",
                "Adequada": {
                    "historia_de_credito": {
                        "Desconhecida": {
                            "divida": {
                                "Baixa": "Baixo",
                                "Alta": "Moderado"
                            }
                        },
                        "Ruim": "Moderado",
                        "Boa": "Baixo"
                    }
                }
            }
        }
    }
}